alyx_registrator-0.0.6.dist-info/METADATA
alyx_registrator-0.0.6.dist-info/WHEEL
one_registrator/README.md
one_registrator/__init__.py
one_registrator/registration.py
one_registrator/rules.json
one_registrator/utils.py
alyx_registrator-0.0.6.dist-info/RECORD
