Metadata-Version: 2.1
Name: alyx-registrator
Version: 0.0.6
Summary: Utilitaries to easily register files to an alyx-database/ONE environment.
Author-Email: Timothe Jost-Mousseau <timothe.jost-mousseau@pasteur.com>
License: MIT
Requires-Python: >=3.11
Requires-Dist: numpy>=1.23
Requires-Dist: alyx-connector>=1.16
Requires-Dist: pandas>=1.4
